nxbc/__init__.py
nxbc/filter.py
nxbc/masks.py
nxbc/plotsupport.py
nxbc/smoothing.py
nxbc-0.2.0.data/scripts/nxbc
nxbc-0.2.0.data/scripts/nxbc-sharpenonly
nxbc-0.2.0.dist-info/LICENSE.txt
nxbc-0.2.0.dist-info/METADATA
nxbc-0.2.0.dist-info/WHEEL
nxbc-0.2.0.dist-info/top_level.txt
nxbc-0.2.0.dist-info/RECORD
