Metadata-Version: 2.1
Name: nxbc
Version: 0.2.0
Summary: NX Bias Correction. NIfTI image bias correction, implementation of N3 (Sled) and N4 (Tustison) algorithms
Home-page: https://github.com/imalone/nxbc.git
Author: Ian Malone
Author-email: i.malone@ucl.ac.uk
License: LICENSE.txt
Classifier: License :: OSI Approved :: BSD License
License-File: LICENSE.txt
Requires-Dist: SplineSmooth3D >=0.1.0
Requires-Dist: nibabel >=2.5.1
Requires-Dist: scikit-image >=0.15.0
Requires-Dist: matplotlib >=3.1.1
Requires-Dist: numpy >=1.17.2
Requires-Dist: scipy >=1.3.1
